flask_arango.py
setup.py
Flask_Arango.egg-info/PKG-INFO
Flask_Arango.egg-info/SOURCES.txt
Flask_Arango.egg-info/dependency_links.txt
Flask_Arango.egg-info/not-zip-safe
Flask_Arango.egg-info/pbr.json
Flask_Arango.egg-info/requires.txt
Flask_Arango.egg-info/top_level.txt