Metadata-Version: 1.1
Name: Flask-Arango
Version: 0.1.1
Summary: Flask extension providing integration with Arango.
Home-page: https://github.com/grucin/flask-arango
Author: Grzegorz Rucinski
Author-email: grucin@gmail.com
License: Apache License, 2.0
Platform: UNKNOWN
Classifier: Intended Audience :: Developers
Classifier: Natural Language :: English
Classifier: Environment :: Web Environment
Classifier: Intended Audience :: Developers
Classifier: License :: OSI Approved :: Apache Software License
Classifier: Operating System :: OS Independent
Classifier: Programming Language :: Python
Classifier: Topic :: Internet :: WWW/HTTP :: Dynamic Content
Classifier: Topic :: Software Development :: Libraries :: Python Modules
